tensorflow_nearest_neighbours/__init__.py
tensorflow_nearest_neighbours/_nearest_neighbours_op.so
tensorflow_nearest_neighbours/python/__init__.py
tensorflow_nearest_neighbours/python/nearest_neighbours.py
test/__init__.py
test/nearest_neighbours_test.py
tensorflow_nearest_neighbours-0.0.6.dist-info/LICENSE
tensorflow_nearest_neighbours-0.0.6.dist-info/METADATA
tensorflow_nearest_neighbours-0.0.6.dist-info/WHEEL
tensorflow_nearest_neighbours-0.0.6.dist-info/top_level.txt
tensorflow_nearest_neighbours-0.0.6.dist-info/RECORD
